lib4vex/__init__.py
lib4vex/generator.py
lib4vex/parser.py
lib4vex/version.py
lib4vex/csaf/__init__.py
lib4vex/csaf/csaf_generator.py
lib4vex/csaf/csaf_parser.py
lib4vex/cyclonedx/__init__.py
lib4vex/cyclonedx/cyclonedx_generator.py
lib4vex/cyclonedx/cyclonedx_parser.py
lib4vex/data/__init__.py
lib4vex/data/document.py
lib4vex/data/metadata.py
lib4vex/data/product.py
lib4vex/data/vulnerability.py
lib4vex/openvex/__init__.py
lib4vex/openvex/openvex_generator.py
lib4vex/openvex/openvex_parser.py
lib4vex/spdx/__init__.py
lib4vex/spdx/spdx_generator.py
lib4vex/spdx/spdx_parser.py
lib4vex-0.2.1.dist-info/LICENSE
lib4vex-0.2.1.dist-info/METADATA
lib4vex-0.2.1.dist-info/WHEEL
lib4vex-0.2.1.dist-info/top_level.txt
lib4vex-0.2.1.dist-info/RECORD
